module1_ibuf_monitor/ibuf_monitor.sv

// GREEN-V PROJECT — Step 1 of 5 (Reactive Sensor)
// ibuf_monitor.sv — 4-State FSM with 8-Cycle Hysteresis Counter
// What this does vs the original:
//   BEFORE: Pure combinational threshold — thrashes on noisy occupancy
//   NOW:    Proper 4-state FSM — state only changes after threshold is held
//           for HYSTERESIS_CYCLES consecutive cycles. No false transitions.
// States:
//   S_IDLE       — occupancy <  5  — CMD_IDLE  (memory stall, clock floor)
//   S_DOWN       — occupancy < 19  — CMD_DOWN  (computational slack)
//   S_HOLD       — occupancy < 55  — CMD_HOLD  (balanced)
//   S_UP         — occupancy >= 55 — CMD_UP    (execution units saturated)
//
// Hysteresis:
//   A pending state change requires the new threshold condition to be true
//   for HYSTERESIS_CYCLES (8) consecutive cycles before the FSM commits.
//   If the condition drops before the counter expires, counter resets.
//   This prevents oscillation on noisy / borderline occupancy values.
//
// Outputs:
//   scale_cmd   [1:0] — command encoding (same as before)
//   scale_valid [0]   — 1-cycle pulse on state change


module ibuf_monitor (
    input  logic       clk,
    input  logic       rst_n,
    input  logic [6:0] occupancy,      // 0-127, buffer fill count
    output logic [1:0] scale_cmd,      // 00=IDLE 01=DOWN 10=HOLD 11=UP
    output logic       scale_valid     // 1-cycle pulse on state change
);

    // -------------------------------------------------------------------------
    // Command encodings
    // -------------------------------------------------------------------------
    localparam logic [1:0] CMD_IDLE = 2'b00;
    localparam logic [1:0] CMD_DOWN = 2'b01;
    localparam logic [1:0] CMD_HOLD = 2'b10;
    localparam logic [1:0] CMD_UP   = 2'b11;

    // -------------------------------------------------------------------------
    // FSM state encoding
    // -------------------------------------------------------------------------
    localparam logic [1:0] S_IDLE = 2'b00;
    localparam logic [1:0] S_DOWN = 2'b01;
    localparam logic [1:0] S_HOLD = 2'b10;
    localparam logic [1:0] S_UP   = 2'b11;

    // -------------------------------------------------------------------------
    // Thresholds (based on 7-bit occupancy, max=127, buffer depth=64)
    // Report values: IDLE<5, DOWN<30%, HOLD 30-85%, UP>85%
    // At depth 64: 5%, 30%, 85% = 4, 19, 55
    // -------------------------------------------------------------------------
    localparam logic [6:0] THR_IDLE = 7'd4;   // < 5   → IDLE
    localparam logic [6:0] THR_DOWN = 7'd19;  // < 30% → DOWN
    localparam logic [6:0] THR_UP   = 7'd55;  // > 85% → UP
    // HOLD is the band between THR_DOWN and THR_UP

    // -------------------------------------------------------------------------
    // Hysteresis depth — must hold new condition for this many cycles
    // -------------------------------------------------------------------------
    localparam integer HYSTERESIS_CYCLES = 8;

    // -------------------------------------------------------------------------
    // Internal registers
    // -------------------------------------------------------------------------
    logic [1:0] state;          // current FSM state
    logic [1:0] pending_state;  // state we are trying to transition to
    logic [3:0] hyst_count;     // hysteresis counter (0-8)

    // -------------------------------------------------------------------------
    // Combinational: what state does the current occupancy suggest?
    // -------------------------------------------------------------------------
    logic [1:0] suggested_state;
    always_comb begin
        if      (occupancy <= THR_IDLE) suggested_state = S_IDLE;
        else if (occupancy <= THR_DOWN) suggested_state = S_DOWN;
        else if (occupancy <  THR_UP  ) suggested_state = S_HOLD;
        else                            suggested_state = S_UP;
    end

    // -------------------------------------------------------------------------
    // FSM with hysteresis counter
    // -------------------------------------------------------------------------
    always_ff @(posedge clk or negedge rst_n) begin
        if (!rst_n) begin
            state         <= S_HOLD;      // safe default — hold current freq
            pending_state <= S_HOLD;
            hyst_count    <= 4'd0;
            scale_cmd     <= CMD_HOLD;
            scale_valid   <= 1'b0;
        end else begin
            scale_valid <= 1'b0;  // default: no pulse

            if (suggested_state == state) begin
                // Already in the right state — reset counter and pending
                hyst_count    <= 4'd0;
                pending_state <= state;
            end else begin
                // Threshold crossed — check if same direction as pending
                if (suggested_state == pending_state) begin
                    // Same target — increment counter
                    if (hyst_count >= HYSTERESIS_CYCLES - 1) begin
                        // Counter expired — commit the transition
                        state         <= suggested_state;
                        pending_state <= suggested_state;
                        hyst_count    <= 4'd0;
                        scale_valid   <= 1'b1;  // pulse on transition
                        // Update command output
                        case (suggested_state)
                            S_IDLE: scale_cmd <= CMD_IDLE;
                            S_DOWN: scale_cmd <= CMD_DOWN;
                            S_HOLD: scale_cmd <= CMD_HOLD;
                            S_UP:   scale_cmd <= CMD_UP;
                        endcase
                    end else begin
                        hyst_count <= hyst_count + 1;
                    end
                end else begin
                    // Different target than pending — reset and start fresh
                    pending_state <= suggested_state;
                    hyst_count    <= 4'd1;
                end
            end
        end
    end

endmodule

module1_ibuf_monitor/tb_ibuf_monitor.sv
`timescale 1ns/1ps
// =============================================================================
// GREEN-V — tb_ibuf_monitor.sv (v2 — FSM + hysteresis verification)
//
// Tests:
//   TEST 1 — No false transition on brief threshold crossing (hysteresis)
//   TEST 2 — Transition commits after 8 sustained cycles
//   TEST 3 — Counter resets if signal drops before 8 cycles
//   TEST 4 — All 4 state transitions: HOLD→UP, UP→HOLD, HOLD→DOWN, DOWN→IDLE
//   TEST 5 — Noisy occupancy around threshold — no thrashing
//   TEST 6 — scale_valid fires exactly once per transition
// =============================================================================

module tb_ibuf_monitor;

    logic       clk, rst_n;
    logic [6:0] occupancy;
    logic [1:0] scale_cmd;
    logic       scale_valid;

    ibuf_monitor dut (.*);

    initial clk = 0;
    always #5 clk = ~clk; // 100MHz

    // Pass/Fail
    integer pass_count = 0;
    integer fail_count = 0;
    task pass(input string msg); $display("  [PASS] %s", msg); pass_count++; endtask
    task fail(input string msg); $display("  [FAIL] %s", msg); fail_count++; endtask

    // Drive occupancy for N cycles
    task drive(input [6:0] occ, input integer cycles);
        occupancy = occ;
        repeat(cycles) @(posedge clk);
    endtask

    // Wait for scale_valid pulse, timeout after max_cycles
    task wait_valid(input integer max_cycles, output logic got_it);
        got_it = 0;
        repeat(max_cycles) begin
            @(posedge clk);
            if (scale_valid && !got_it) got_it = 1;
        end
    endtask

    logic [1:0] cmd_before;
    logic got_valid;
    integer valid_count;

    initial begin
        $dumpfile("ibuf_sim_v2.vcd");
        $dumpvars(0, tb_ibuf_monitor);

        rst_n = 0; occupancy = 7'd30; // HOLD zone
        repeat(5) @(posedge clk);
        rst_n = 1;
        repeat(3) @(posedge clk);

        $display("\n=== GREEN-V ibuf_monitor FSM + Hysteresis Testbench ===\n");

        // =====================================================================
        // TEST 1: Brief threshold crossing — should NOT trigger transition
        // Cross into UP zone for only 4 cycles (less than hysteresis=8)
        // scale_cmd must NOT change
        // =====================================================================
        $display("--- TEST 1: Brief crossing — no false transition ---");
        drive(7'd30, 5); // settle in HOLD
        cmd_before = scale_cmd;
        drive(7'd60, 4); // cross UP threshold for only 4 cycles
        drive(7'd30, 5); // drop back
        if (scale_cmd == cmd_before)
            pass("scale_cmd unchanged after 4-cycle crossing (hysteresis blocked)");
        else
            fail("scale_cmd changed on brief crossing — hysteresis not working");

        // =====================================================================
        // TEST 2: Sustained crossing — should commit after 8 cycles
        // =====================================================================
        $display("\n--- TEST 2: Sustained crossing commits after 8 cycles ---");
        drive(7'd30, 5); // settle in HOLD
        cmd_before = scale_cmd;

        // Drive UP zone for 10 cycles — should commit at cycle 8
        occupancy = 7'd60;
        valid_count = 0;
        repeat(12) begin
            @(posedge clk);
            if (scale_valid) valid_count++;
        end

        if (scale_cmd == 2'b11)
            pass("scale_cmd = CMD_UP after sustained crossing");
        else
            fail("scale_cmd did not reach CMD_UP after 12 cycles");

        if (valid_count == 1)
            pass("scale_valid fired exactly once during transition");
        else begin
            $display("  [INFO] scale_valid fired %0d times", valid_count);
            if (valid_count > 1)
                fail("scale_valid fired multiple times — thrashing");
        end

        // =====================================================================
        // TEST 3: Counter resets if signal drops before committing
        // Cross threshold for 6 cycles, drop, cross again — should need
        // another full 8 cycles from the drop point
        // =====================================================================
        $display("\n--- TEST 3: Counter resets on signal dropout ---");
        drive(7'd30, 5); // back to HOLD — wait for it to commit
        repeat(15) @(posedge clk); // give FSM time to settle back to HOLD

        cmd_before = scale_cmd;
        drive(7'd60, 6); // cross UP for 6 cycles (not enough)
        drive(7'd30, 3); // drop back — counter should reset
        drive(7'd60, 4); // cross again for only 4 more cycles
        drive(7'd30, 5); // drop

        // Should still be in HOLD — 6+4 with a gap doesn't count as 8 sustained
        if (scale_cmd == 2'b10 || scale_cmd == cmd_before)
            pass("Counter reset on dropout — no premature transition");
        else
            fail("Transition happened despite non-sustained crossing");

        // =====================================================================
        // TEST 4: All 4 state transitions
        // =====================================================================
        $display("\n--- TEST 4: All 4 state transitions ---");

        // HOLD → UP
        drive(7'd30, 3);
        repeat(20) @(posedge clk); // let it settle
        drive(7'd60, 10);
        if (scale_cmd == 2'b11) pass("HOLD -> UP transition");
        else fail("HOLD -> UP failed");

        // UP → HOLD
        drive(7'd35, 10);
        if (scale_cmd == 2'b10) pass("UP -> HOLD transition");
        else fail("UP -> HOLD failed");

        // HOLD → DOWN
        drive(7'd10, 10);
        if (scale_cmd == 2'b01) pass("HOLD -> DOWN transition");
        else fail("HOLD -> DOWN failed");

        // DOWN → IDLE
        drive(7'd2, 10);
        if (scale_cmd == 2'b00) pass("DOWN -> IDLE transition");
        else fail("DOWN -> IDLE failed");

        // IDLE → HOLD (recovery)
        drive(7'd35, 10);
        if (scale_cmd == 2'b10) pass("IDLE -> HOLD recovery");
        else fail("IDLE -> HOLD recovery failed");

        // =====================================================================
        // TEST 5: Noisy signal around threshold — no thrashing
        // Oscillate occupancy around the UP threshold (55) every 2 cycles
        // With hysteresis, scale_cmd should NOT toggle repeatedly
        // =====================================================================
        $display("\n--- TEST 5: Noisy signal — no thrashing ---");
        drive(7'd35, 5); // settle in HOLD
        repeat(15) @(posedge clk);

        valid_count = 0;
        // Noise: alternate 52 and 58 every 2 cycles for 32 cycles
        for (int ii = 0; ii < 16; ii++) begin
            drive(7'd58, 2); // just above threshold
            drive(7'd52, 2); // just below threshold
            if (scale_valid) valid_count++;
        end

        $display("  scale_valid fired %0d times during 32 cycles of noise", valid_count);
        if (valid_count <= 1)
            pass("No thrashing on noisy signal around threshold");
        else
            fail("Thrashing detected — hysteresis not wide enough");

        // =====================================================================
        // RESULTS
        // =====================================================================
        $display("\n=== RESULTS: %0d passed, %0d failed ===", pass_count, fail_count);
        if (fail_count == 0)
            $display("ALL TESTS PASSED\n");
        else
            $display("CHECK WAVEFORM: gtkwave ibuf_sim_v2.vcd\n");

        $finish;
    end

    initial begin #500000; $display("[WATCHDOG] Timeout"); $finish; end

endmodule

module1_ibuf_monitor/ibuf_sim_v2.vcd
$date
	Sat Mar  7 09:03:31 2026
$end
$version
	Icarus Verilog
$end
$timescale
	1ps
$end
$scope module tb_ibuf_monitor $end
$var wire 1 ! scale_valid $end
$var wire 2 " scale_cmd [1:0] $end
$var reg 1 # clk $end
$var reg 2 $ cmd_before [1:0] $end
$var reg 7 % occupancy [6:0] $end
$var reg 1 & rst_n $end
$var integer 32 ' fail_count [31:0] $end
$var integer 32 ( pass_count [31:0] $end
$var integer 32 ) valid_count [31:0] $end
$scope module dut $end
$var wire 1 # clk $end
$var wire 7 * occupancy [6:0] $end
$var wire 1 & rst_n $end
$var parameter 2 + CMD_DOWN $end
$var parameter 2 , CMD_HOLD $end
$var parameter 2 - CMD_IDLE $end
$var parameter 2 . CMD_UP $end
$var parameter 32 / HYSTERESIS_CYCLES $end
$var parameter 2 0 S_DOWN $end
$var parameter 2 1 S_HOLD $end
$var parameter 2 2 S_IDLE $end
$var parameter 2 3 S_UP $end
$var parameter 7 4 THR_DOWN $end
$var parameter 7 5 THR_IDLE $end
$var parameter 7 6 THR_UP $end
$var reg 4 7 hyst_count [3:0] $end
$var reg 2 8 pending_state [1:0] $end
$var reg 2 9 scale_cmd [1:0] $end
$var reg 1 ! scale_valid $end
$var reg 2 : state [1:0] $end
$var reg 2 ; suggested_state [1:0] $end
$upscope $end
$scope begin $ivl_for_loop0 $end
$var integer 32 < ii [31:0] $end
$upscope $end
$scope task drive $end
$var reg 7 = occ [6:0] $end
$var integer 32 > cycles [31:0] $end
$upscope $end
$scope task fail $end
$upscope $end
$scope task pass $end
$upscope $end
$scope task wait_valid $end
$var reg 1 ? got_it $end
$var integer 32 @ max_cycles [31:0] $end
$upscope $end
$upscope $end
$enddefinitions $end
$comment Show the parameter values. $end
$dumpall
b110111 6
b100 5
b10011 4
b11 3
b0 2
b10 1
b1 0
b1000 /
b11 .
b0 -
b10 ,
b1 +
$end
#0
$dumpvars
bx @
x?
bx >
bx =
b0 <
b10 ;
b10 :
b10 9
b10 8
b0 7
b11110 *
bx )
b0 (
b0 '
0&
b11110 %
bx $
0#
b10 "
0!
$end
#5000
1#
#10000
0#
#15000
1#
#20000
0#
#25000
1#
#30000
0#
#35000
1#
#40000
0#
#45000
1&
1#
#50000
0#
#55000
1#
#60000
0#
#65000
1#
#70000
0#
#75000
b101 >
b11110 =
1#
#80000
0#
#85000
1#
#90000
0#
#95000
1#
#100000
0#
#105000
1#
#110000
0#
#115000
1#
#120000
0#
#125000
b11 ;
b111100 %
b111100 *
b100 >
b111100 =
b10 $
1#
#130000
0#
#135000
b1 7
b11 8
1#
#140000
0#
#145000
b10 7
1#
#150000
0#
#155000
b11 7
1#
#160000
0#
#165000
b100 7
b10 ;
b11110 %
b11110 *
b101 >
b11110 =
1#
#170000
0#
#175000
b10 8
b0 7
1#
#180000
0#
#185000
1#
#190000
0#
#195000
1#
#200000
0#
#205000
1#
#210000
0#
#215000
b1 (
1#
#220000
0#
#225000
1#
#230000
0#
#235000
1#
#240000
0#
#245000
1#
#250000
0#
#255000
1#
#260000
0#
#265000
b11 ;
b0 )
b111100 %
b111100 *
1#
#270000
0#
#275000
b1 7
b11 8
1#
#280000
0#
#285000
b10 7
1#
#290000
0#
#295000
b11 7
1#
#300000
0#
#305000
b100 7
1#
#310000
0#
#315000
b101 7
1#
#320000
0#
#325000
b110 7
1#
#330000
0#
#335000
b111 7
1#
#340000
0#
#345000
b11 "
b11 9
1!
b0 7
b11 :
1#
#350000
0#
#355000
0!
b1 )
1#
#360000
0#
#365000
1#
#370000
0#
#375000
1#
#380000
0#
#385000
b10 ;
b11110 %
b11110 *
b11 (
1#
#390000
0#
#395000
b1 7
b10 8
1#
#400000
0#
#405000
b10 7
1#
#410000
0#
#415000
b11 7
1#
#420000
0#
#425000
b100 7
1#
#430000
0#
#435000
b101 7
1#
#440000
0#
#445000
b110 7
1#
#450000
0#
#455000
b111 7
1#
#460000
0#
#465000
b10 "
b10 9
1!
b0 7
b10 :
1#
#470000
0#
#475000
0!
1#
#480000
0#
#485000
1#
#490000
0#
#495000
1#
#500000
0#
#505000
1#
#510000
0#
#515000
1#
#520000
0#
#525000
1#
#530000
0#
#535000
1#
#540000
0#
#545000
1#
#550000
0#
#555000
1#
#560000
0#
#565000
1#
#570000
0#
#575000
1#
#580000
0#
#585000
b11 ;
b111100 %
b111100 *
b110 >
b111100 =
1#
#590000
0#
#595000
b1 7
b11 8
1#
#600000
0#
#605000
b10 7
1#
#610000
0#
#615000
b11 7
1#
#620000
0#
#625000
b100 7
1#
#630000
0#
#635000
b101 7
1#
#640000
0#
#645000
b110 7
b10 ;
b11110 %
b11110 *
b11 >
b11110 =
1#
#650000
0#
#655000
b10 8
b0 7
1#
#660000
0#
#665000
1#
#670000
0#
#675000
b11 ;
b111100 %
b111100 *
b100 >
b111100 =
1#
#680000
0#
#685000
b1 7
b11 8
1#
#690000
0#
#695000
b10 7
1#
#700000
0#
#705000
b11 7
1#
#710000
0#
#715000
b100 7
b10 ;
b11110 %
b11110 *
b101 >
b11110 =
1#
#720000
0#
#725000
b10 8
b0 7
1#
#730000
0#
#735000
1#
#740000
0#
#745000
1#
#750000
0#
#755000
1#
#760000
0#
#765000
b11 >
b100 (
1#
