module4_lookahead_unit/lookahead_unit.sv
// =============================================================================
// GREEN-V PROJECT — Step 4 of 5 (Predictive Path - SystemVerilog)
// lookahead_unit.sv — 8-Instruction Window Scanner
//
// What this does:
//   - Accepts 8 fetched instructions simultaneously (inst_window[7:0][31:0])
//   - Scans all 8 in parallel combinationally — zero latency detection
//   - Detects: loops, integer compute bursts, FP ops, load/store sequences,
//              branch clusters
//   - Uses a weighted vote across the window — not just slot[0]
//   - Fires spike_detected if 2+ high-intensity instructions in the window
//   - Fires CMD_DOWN if window is dominated by memory/load ops
//   - Fires CMD_UP if window has significant compute density
//
// Port change from v1:
//   inst_window : [31:0]       -> [7:0][31:0]   (8 instructions)
//   inst_valid  : single bit   -> unchanged
// =============================================================================

module lookahead_unit (
    input  logic        clk,
    input  logic        rst_n,
    input  logic [31:0] inst_window [7:0],  // 8 fetched instructions
    input  logic        inst_valid,
    output logic [1:0]  lookahead_cmd,       // 00=IDLE 01=DOWN 10=HOLD 11=UP
    output logic        spike_detected
);

    // -------------------------------------------------------------------------
    // Command encodings
    // -------------------------------------------------------------------------
    localparam logic [1:0] CMD_IDLE = 2'b00;
    localparam logic [1:0] CMD_DOWN = 2'b01;
    localparam logic [1:0] CMD_HOLD = 2'b10;
    localparam logic [1:0] CMD_UP   = 2'b11;

    // -------------------------------------------------------------------------
    // RISC-V opcode field = bits [6:0]
    // -------------------------------------------------------------------------
    localparam logic [6:0] OP_BRANCH  = 7'b1100011; // BEQ/BNE/BLT -- loop indicator
    localparam logic [6:0] OP_INT_R   = 7'b0110011; // ADD/SUB/AND/OR/MUL -- compute
    localparam logic [6:0] OP_INT_I   = 7'b0010011; // ADDI/SLTI/XORI -- compute
    localparam logic [6:0] OP_LOAD    = 7'b0000011; // LW/LH/LB -- memory stall
    localparam logic [6:0] OP_STORE   = 7'b0100011; // SW/SH/SB -- memory stall
    localparam logic [6:0] OP_FP_R    = 7'b1010011; // FADD/FMUL/FDIV -- FP burst
    localparam logic [6:0] OP_FP_LOAD = 7'b0000111; // FLW/FLD -- FP memory
    localparam logic [6:0] OP_MADD    = 7'b1000011; // FMADD -- matrix/FP intensive

    // -------------------------------------------------------------------------
    // Per-slot pattern flags (combinational -- all 8 slots in parallel)
    // -------------------------------------------------------------------------
    logic [7:0] slot_is_branch;
    logic [7:0] slot_is_compute;
    logic [7:0] slot_is_mem;
    logic [7:0] slot_is_fp;
    logic [7:0] slot_is_madd;

    genvar i;
    generate
        for (i = 0; i < 8; i++) begin : pattern_detect
            assign slot_is_branch [i] = (inst_window[i][6:0] == OP_BRANCH);
            assign slot_is_compute[i] = (inst_window[i][6:0] == OP_INT_R) |
                                        (inst_window[i][6:0] == OP_INT_I);
            assign slot_is_mem    [i] = (inst_window[i][6:0] == OP_LOAD)  |
                                        (inst_window[i][6:0] == OP_STORE);
            assign slot_is_fp     [i] = (inst_window[i][6:0] == OP_FP_R)  |
                                        (inst_window[i][6:0] == OP_FP_LOAD);
            assign slot_is_madd   [i] = (inst_window[i][6:0] == OP_MADD);
        end
    endgenerate

    // -------------------------------------------------------------------------
    // Population counts -- how many of each type in the window
    // -------------------------------------------------------------------------
    logic [3:0] cnt_branch;
    logic [3:0] cnt_compute;
    logic [3:0] cnt_mem;
    logic [3:0] cnt_fp;
    logic [3:0] cnt_madd;

    always_comb begin
        cnt_branch  = 4'd0;
        cnt_compute = 4'd0;
        cnt_mem     = 4'd0;
        cnt_fp      = 4'd0;
        cnt_madd    = 4'd0;
        for (int j = 0; j < 8; j++) begin
            cnt_branch  = cnt_branch  + {3'b0, slot_is_branch [j]};
            cnt_compute = cnt_compute + {3'b0, slot_is_compute[j]};
            cnt_mem     = cnt_mem     + {3'b0, slot_is_mem    [j]};
            cnt_fp      = cnt_fp      + {3'b0, slot_is_fp     [j]};
            cnt_madd    = cnt_madd    + {3'b0, slot_is_madd   [j]};
        end
    end

    // -------------------------------------------------------------------------
    // Decision logic (combinational)
    // spike: branch + compute body, FP burst, or matrix op
    // CMD_UP: any spike, or compute-heavy window
    // CMD_DOWN: memory-dominated window
    // CMD_HOLD: balanced / mixed
    // -------------------------------------------------------------------------
    logic comb_spike;
    logic [1:0] comb_cmd;

    always_comb begin
        comb_spike = 1'b0;
        if ((cnt_branch >= 4'd1 && cnt_compute >= 4'd2) ||
            (cnt_fp     >= 4'd2)                         ||
            (cnt_madd   >= 4'd1))
            comb_spike = 1'b1;

        if (comb_spike || cnt_compute >= 4'd3 || cnt_fp >= 4'd1)
            comb_cmd = CMD_UP;
        else if (cnt_mem >= 4'd4 && cnt_compute == 4'd0 && cnt_fp == 4'd0)
            comb_cmd = CMD_DOWN;
        else if (cnt_mem >= 4'd2 && cnt_compute <= 4'd1)
            comb_cmd = CMD_DOWN;
        else
            comb_cmd = CMD_HOLD;
    end

    // -------------------------------------------------------------------------
    // Registered outputs
    // -------------------------------------------------------------------------
    always_ff @(posedge clk or negedge rst_n) begin
        if (!rst_n) begin
            lookahead_cmd  <= CMD_HOLD;
            spike_detected <= 1'b0;
        end else begin
            spike_detected <= 1'b0;
            lookahead_cmd  <= CMD_HOLD;
            if (inst_valid) begin
                lookahead_cmd  <= comb_cmd;
                spike_detected <= comb_spike;
            end
        end
    end

endmodule

module4_lookahead_unit/tb_lookahead_unit.sv
`timescale 1ns/1ps
// =============================================================================
// GREEN-V — tb_lookahead_unit.sv (v2 — 8-instruction window)
//
// Tests every detection path in the fixed lookahead_unit:
//   TEST 1  — Reset: outputs HOLD, no spike
//   TEST 2  — inst_valid=0: outputs stay HOLD regardless of window
//   TEST 3  — Loop spike: branch + 2 math ops -> spike_detected + CMD_UP
//   TEST 4  — Loop threshold: branch + 1 math (below threshold) -> no spike
//   TEST 5  — FP burst spike: 2+ FP ops -> spike_detected + CMD_UP
//   TEST 6  — Single FP: 1 FP op -> CMD_UP but no spike
//   TEST 7  — MADD spike: 1 matrix op -> spike_detected + CMD_UP
//   TEST 8  — Compute burst: 3+ INT ops, no branch -> CMD_UP, no spike
//   TEST 9  — Memory dominated: 4+ loads, no compute -> CMD_DOWN
//   TEST 10 — Light memory: 2 loads, 1 compute -> CMD_DOWN
//   TEST 11 — Mixed window: balanced compute + mem -> CMD_HOLD
//   TEST 12 — NOP stream: all NOPs -> CMD_HOLD, no spike
//   TEST 13 — spike_detected is 1-cycle pulse only
//   TEST 14 — All 8 slots scanned: spike from slot[7] not slot[0]
// =============================================================================

module tb_lookahead_unit;

    logic        clk, rst_n, inst_valid;
    logic [31:0] inst_window [7:0];
    logic [1:0]  lookahead_cmd;
    logic        spike_detected;

    lookahead_unit dut (
        .clk          (clk),
        .rst_n        (rst_n),
        .inst_window  (inst_window),
        .inst_valid   (inst_valid),
        .lookahead_cmd(lookahead_cmd),
        .spike_detected(spike_detected)
    );

    initial clk = 0;
    always #5 clk = ~clk; // 100MHz

    // -------------------------------------------------------------------------
    // Instruction encodings — only lower 7 bits matter for opcode detection
    // -------------------------------------------------------------------------
    localparam [31:0] INST_NOP    = 32'h0000007F; // opcode 0x7F — reserved, matches no pattern
    localparam [31:0] INST_BRANCH = 32'h00000063; // opcode 0x63 — branch
    localparam [31:0] INST_MATH   = 32'h00000033; // opcode 0x33 — INT R-type
    localparam [31:0] INST_IMATH  = 32'h00000013; // opcode 0x13 — INT I-type (NOP slot)
    localparam [31:0] INST_LOAD   = 32'h00000003; // opcode 0x03 — load
    localparam [31:0] INST_STORE  = 32'h00000023; // opcode 0x23 — store
    localparam [31:0] INST_FP     = 32'h00000053; // opcode 0x53 — FP R-type
    localparam [31:0] INST_FLOAD  = 32'h00000007; // opcode 0x07 — FP load
    localparam [31:0] INST_MADD   = 32'h00000043; // opcode 0x43 — FMADD

    // -------------------------------------------------------------------------
    // Pass/Fail
    // -------------------------------------------------------------------------
    integer pass_count = 0;
    integer fail_count = 0;
    task pass(input string msg); $display("  [PASS] %s", msg); pass_count++; endtask
    task fail(input string msg); $display("  [FAIL] %s", msg); fail_count++; endtask

    // -------------------------------------------------------------------------
    // Helper: fill all 8 slots with same opcode
    // -------------------------------------------------------------------------
    task fill_all(input [31:0] opcode);
        for (int k = 0; k < 8; k++) inst_window[k] = opcode;
    endtask

    // -------------------------------------------------------------------------
    // Helper: send window and wait one cycle for registered output
    // -------------------------------------------------------------------------
    task send_window_and_wait;
        @(posedge clk);
        inst_valid <= 1;
        @(posedge clk); // outputs register here
        inst_valid <= 0;
        @(posedge clk); // read outputs this cycle
    endtask

    // -------------------------------------------------------------------------
    // SIMULATION
    // -------------------------------------------------------------------------
    initial begin
        $dumpfile("lookahead_sim_v2.vcd");
        $dumpvars(0, tb_lookahead_unit);

        // Init
        clk=0; rst_n=0; inst_valid=0;
        fill_all(INST_NOP);

        repeat(5) @(posedge clk);
        rst_n = 1;
        repeat(3) @(posedge clk);

        $display("\n=== GREEN-V lookahead_unit Testbench v2 ===\n");

        // =====================================================================
        // TEST 1: Reset state
        // =====================================================================
        $display("--- TEST 1: Reset state ---");
        if (lookahead_cmd == 2'b10)
            pass("lookahead_cmd = HOLD after reset");
        else
            fail("lookahead_cmd wrong after reset");
        if (spike_detected == 0)
            pass("spike_detected = 0 after reset");
        else
            fail("spike_detected high after reset");

        // =====================================================================
        // TEST 2: inst_valid=0 — window ignored
        // =====================================================================
        $display("\n--- TEST 2: inst_valid=0 — window ignored ---");
        // Load a spike-worthy window but don't assert inst_valid
        inst_window[0] = INST_BRANCH;
        inst_window[1] = INST_MATH;
        inst_window[2] = INST_MATH;
        inst_window[3] = INST_MATH;
        for (int k=4; k<8; k++) inst_window[k] = INST_NOP;
        inst_valid = 0;
        repeat(3) @(posedge clk);

        if (spike_detected == 0)
            pass("spike_detected stays 0 when inst_valid=0");
        else
            fail("spike_detected fired without inst_valid");
        if (lookahead_cmd == 2'b10)
            pass("lookahead_cmd stays HOLD when inst_valid=0");
        else
            fail("lookahead_cmd changed without inst_valid");

        // =====================================================================
        // TEST 3: Loop spike — branch + 2 math ops
        // =====================================================================
        $display("\n--- TEST 3: Loop spike (branch + 2 math) ---");
        inst_window[0] = INST_BRANCH;
        inst_window[1] = INST_MATH;
        inst_window[2] = INST_MATH;
        inst_window[3] = INST_NOP;
        inst_window[4] = INST_NOP;
        inst_window[5] = INST_NOP;
        inst_window[6] = INST_NOP;
        inst_window[7] = INST_NOP;
        send_window_and_wait;

        if (spike_detected)
            pass("spike_detected fired on loop pattern (branch + 2 math)");
        else
            fail("spike_detected did not fire on loop pattern");
        if (lookahead_cmd == 2'b11)
            pass("lookahead_cmd = CMD_UP on loop pattern");
        else
            fail("lookahead_cmd wrong on loop pattern");

        // =====================================================================
        // TEST 4: Branch + 1 math only — below spike threshold
        // =====================================================================
        $display("\n--- TEST 4: Branch + 1 math — no spike (below threshold) ---");
        fill_all(INST_NOP);
        inst_window[0] = INST_BRANCH;
        inst_window[1] = INST_MATH;
        send_window_and_wait;

        if (!spike_detected)
            pass("No spike on branch + 1 math (needs 2 math for spike)");
        else
            fail("False spike on branch + 1 math");

        // =====================================================================
        // TEST 5: FP burst spike — 2+ FP ops
        // =====================================================================
        $display("\n--- TEST 5: FP burst spike (2+ FP ops) ---");
        fill_all(INST_NOP);
        inst_window[0] = INST_FP;
        inst_window[1] = INST_FP;
        inst_window[2] = INST_MATH;
        send_window_and_wait;

        if (spike_detected)
            pass("spike_detected fired on FP burst (2 FP ops)");
        else
            fail("spike_detected did not fire on FP burst");
        if (lookahead_cmd == 2'b11)
            pass("lookahead_cmd = CMD_UP on FP burst");
        else
            fail("lookahead_cmd wrong on FP burst");

        // =====================================================================
        // TEST 6: Single FP op — CMD_UP but no spike
        // =====================================================================
        $display("\n--- TEST 6: Single FP op — CMD_UP, no spike ---");
        fill_all(INST_NOP);
        inst_window[0] = INST_FP;
        send_window_and_wait;

        if (!spike_detected)
            pass("No spike on single FP op");
        else
            fail("False spike on single FP op");
        if (lookahead_cmd == 2'b11)
            pass("CMD_UP on single FP op (FP always triggers UP)");
        else
            fail("lookahead_cmd wrong on single FP op");

        // =====================================================================
        // TEST 7: MADD spike — single matrix op triggers spike
        // =====================================================================
        $display("\n--- TEST 7: MADD spike (1 matrix op) ---");
        fill_all(INST_NOP);
        inst_window[3] = INST_MADD; // put it in middle slot
        send_window_and_wait;

        if (spike_detected)
            pass("spike_detected fired on MADD (matrix op)");
        else
            fail("spike_detected did not fire on MADD");

        // =====================================================================
        // TEST 8: Compute burst — 3+ INT ops, no branch, no spike
        // =====================================================================
        $display("\n--- TEST 8: Compute burst (3 INT ops, no branch) ---");
        fill_all(INST_NOP);
        inst_window[0] = INST_MATH;
        inst_window[1] = INST_MATH;
        inst_window[2] = INST_MATH;
        send_window_and_wait;

        if (!spike_detected)
            pass("No spike on 3 INT ops without branch");
        else
            fail("False spike on INT-only window");
        if (lookahead_cmd == 2'b11)
            pass("CMD_UP on 3+ compute ops");
        else
            fail("lookahead_cmd wrong on compute burst");

        // =====================================================================
        // TEST 9: Memory dominated — 4+ loads, no compute -> CMD_DOWN
        // =====================================================================
        $display("\n--- TEST 9: Memory dominated window -> CMD_DOWN ---");
        fill_all(INST_NOP); // clear previous window first
        inst_window[0] = INST_LOAD;
        inst_window[1] = INST_LOAD;
        inst_window[2] = INST_LOAD;
        inst_window[3] = INST_LOAD;
        inst_window[4] = INST_LOAD;
        inst_window[5] = INST_NOP;
        inst_window[6] = INST_NOP;
        inst_window[7] = INST_NOP;
        send_window_and_wait;

        if (lookahead_cmd == 2'b01)
            pass("CMD_DOWN on memory-dominated window (5 loads)");
        else
            fail("lookahead_cmd wrong on memory window");
        if (!spike_detected)
            pass("No spike on memory window");
        else
            fail("False spike on memory window");

        // =====================================================================
        // TEST 10: Light memory — 2 loads, 1 compute -> CMD_DOWN
        // =====================================================================
        $display("\n--- TEST 10: Light memory (2 loads, 1 compute) -> CMD_DOWN ---");
        fill_all(INST_NOP);
        inst_window[0] = INST_LOAD;
        inst_window[1] = INST_LOAD;
        inst_window[2] = INST_MATH;
        send_window_and_wait;

        if (lookahead_cmd == 2'b01)
            pass("CMD_DOWN on 2 loads + 1 compute");
        else
            $display("  [INFO] lookahead_cmd = %02b (borderline case)", lookahead_cmd);

        // =====================================================================
        // TEST 11: Mixed window -> CMD_HOLD
        // =====================================================================
        $display("\n--- TEST 11: Mixed window -> CMD_HOLD ---");
        fill_all(INST_NOP);
        inst_window[0] = INST_MATH;
        inst_window[1] = INST_LOAD;
        inst_window[2] = INST_MATH;
        inst_window[3] = INST_LOAD;
        send_window_and_wait;

        if (lookahead_cmd == 2'b10)
            pass("CMD_HOLD on balanced mixed window");
        else
            $display("  [INFO] lookahead_cmd = %02b on mixed window", lookahead_cmd);

        // =====================================================================
        // TEST 12: NOP stream -> CMD_HOLD, no spike
        // =====================================================================
        $display("\n--- TEST 12: NOP stream -> CMD_HOLD, no spike ---");
        fill_all(INST_NOP);
        send_window_and_wait;

        if (lookahead_cmd == 2'b10)
            pass("CMD_HOLD on NOP stream");
        else
            fail("lookahead_cmd wrong on NOP stream");
        if (!spike_detected)
            pass("No spike on NOP stream");
        else
            fail("False spike on NOP stream");

        // =====================================================================
        // TEST 13: spike_detected is 1-cycle pulse only
        // =====================================================================
        $display("\n--- TEST 13: spike_detected is 1-cycle pulse ---");
        // Send spike window
        fill_all(INST_NOP);
        inst_window[0] = INST_BRANCH;
        inst_window[1] = INST_MATH;
        inst_window[2] = INST_MATH;
        @(posedge clk); inst_valid <= 1;
        @(posedge clk); inst_valid <= 0; // stop sending
        @(posedge clk); // spike should fire here
        // Next cycle — no new valid window — spike must clear
        @(posedge clk);
        if (!spike_detected)
            pass("spike_detected cleared after 1 cycle (pulse only)");
        else
            fail("spike_detected stuck high — not a pulse");

        // =====================================================================
        // TEST 14: Spike detected from slot[7] not slot[0]
        // Proves all 8 slots are scanned, not just the first
        // =====================================================================
        $display("\n--- TEST 14: Spike from slot[7] — all slots scanned ---");
        fill_all(INST_NOP);
        inst_window[7] = INST_MADD; // put trigger in LAST slot only
        send_window_and_wait;

        if (spike_detected)
            pass("spike_detected from slot[7] — full window scanned");
        else
            fail("spike missed in slot[7] — not all slots scanned");

        // =====================================================================
        // RESULTS
        // =====================================================================
        $display("\n=== RESULTS: %0d passed, %0d failed ===", pass_count, fail_count);
        if (fail_count == 0)
            $display("ALL TESTS PASSED\n");
        else
            $display("CHECK WAVEFORM: gtkwave lookahead_sim_v2.vcd\n");

        $finish;
    end

    initial begin #200000; $display("[WATCHDOG] Timeout"); $finish; end

endmodule

module4_lookahead_unit/lookahead_sim_v2.vcd
$date
	Sat Mar  7 14:41:04 2026
$end
$version
	Icarus Verilog
$end
$timescale
	1ps
$end
$scope module tb_lookahead_unit $end
$var wire 1 ! spike_detected $end
$var wire 2 " lookahead_cmd [1:0] $end
$var parameter 32 # INST_BRANCH $end
$var parameter 32 $ INST_FLOAD $end
$var parameter 32 % INST_FP $end
$var parameter 32 & INST_IMATH $end
$var parameter 32 ' INST_LOAD $end
$var parameter 32 ( INST_MADD $end
$var parameter 32 ) INST_MATH $end
$var parameter 32 * INST_NOP $end
$var parameter 32 + INST_STORE $end
$var reg 1 , clk $end
$var reg 1 - inst_valid $end
$var reg 1 . rst_n $end
$var integer 32 / fail_count [31:0] $end
$var integer 32 0 pass_count [31:0] $end
$scope module dut $end
$var wire 1 , clk $end
$var wire 1 - inst_valid $end
$var wire 1 . rst_n $end
$var wire 8 1 slot_is_mem [7:0] $end
$var wire 8 2 slot_is_madd [7:0] $end
$var wire 8 3 slot_is_fp [7:0] $end
$var wire 8 4 slot_is_compute [7:0] $end
$var wire 8 5 slot_is_branch [7:0] $end
$var parameter 2 6 CMD_DOWN $end
$var parameter 2 7 CMD_HOLD $end
$var parameter 2 8 CMD_IDLE $end
$var parameter 2 9 CMD_UP $end
$var parameter 7 : OP_BRANCH $end
$var parameter 7 ; OP_FP_LOAD $end
$var parameter 7 < OP_FP_R $end
$var parameter 7 = OP_INT_I $end
$var parameter 7 > OP_INT_R $end
$var parameter 7 ? OP_LOAD $end
$var parameter 7 @ OP_MADD $end
$var parameter 7 A OP_STORE $end
$var reg 4 B cnt_branch [3:0] $end
$var reg 4 C cnt_compute [3:0] $end
$var reg 4 D cnt_fp [3:0] $end
$var reg 4 E cnt_madd [3:0] $end
$var reg 4 F cnt_mem [3:0] $end
$var reg 2 G comb_cmd [1:0] $end
$var reg 1 H comb_spike $end
$var reg 2 I lookahead_cmd [1:0] $end
$var reg 1 ! spike_detected $end
$scope begin pattern_detect[0] $end
$var parameter 2 J i $end
$upscope $end
$scope begin pattern_detect[1] $end
$var parameter 2 K i $end
$upscope $end
$scope begin pattern_detect[2] $end
$var parameter 3 L i $end
$upscope $end
$scope begin pattern_detect[3] $end
$var parameter 3 M i $end
$upscope $end
$scope begin pattern_detect[4] $end
$var parameter 4 N i $end
$upscope $end
$scope begin pattern_detect[5] $end
$var parameter 4 O i $end
$upscope $end
$scope begin pattern_detect[6] $end
$var parameter 4 P i $end
$upscope $end
$scope begin pattern_detect[7] $end
$var parameter 4 Q i $end
$upscope $end
$scope begin $ivl_for_loop2 $end
$var integer 32 R j [31:0] $end
$upscope $end
$upscope $end
$scope begin $ivl_for_loop1 $end
$var integer 32 S k [31:0] $end
$upscope $end
$scope task fail $end
$upscope $end
$scope task fill_all $end
$var reg 32 T opcode [31:0] $end
$scope begin $ivl_for_loop0 $end
$var integer 32 U k [31:0] $end
$upscope $end
$upscope $end
$scope task pass $end
$upscope $end
$scope task send_window_and_wait $end
$upscope $end
$upscope $end
$enddefinitions $end
$comment Show the parameter values. $end
$dumpall
b111 Q
b110 P
b101 O
b100 N
b11 M
b10 L
b1 K
b0 J
b100011 A
b1000011 @
b11 ?
b110011 >
b10011 =
b1010011 <
b111 ;
b1100011 :
b11 9
b0 8
b10 7
b1 6
b100011 +
b1111111 *
b110011 )
b1000011 (
b11 '
b10011 &
b1010011 %
b111 $
b1100011 #
$end
#0
$dumpvars
b1000 U
b1111111 T
b0 S
b1000 R
b10 I
0H
b10 G
b0 F
b0 E
b0 D
b0 C
b0 B
b0 5
b0 4
b0 3
b0 2
b0 1
b0 0
b0 /
0.
0-
0,
b10 "
0!
$end
#5000
1,
#10000
0,
#15000
1,
#20000
0,
#25000
1,
#30000
0,
#35000
1,
#40000
0,
#45000
1.
1,
#50000
0,
#55000
1,
#60000
0,
#65000
1,
#70000
0,
#75000
b11 G
1H
b11 C
b1110 4
b1 B
b1000 R
b1 5
b1000 S
b10 0
1,
#80000
0,
#85000
1,
#90000
0,
#95000
1,
#100000
0,
#105000
1H
b1000 R
b10 C
b1 B
b110 4
b100 0
1,
#110000
0,
#115000
1-
1,
#120000
0,
#125000
1!
b11 "
b11 I
0-
1,
#130000
0,
#135000
b10 "
b10 I
0!
b10 G
0H
b1000 R
b1 C
b1 B
b10 4
b1000 U
b110 0
1,
#140000
0,
#145000
1-
1,
#150000
0,
#155000
0-
1,
#160000
0,
#165000
1H
b11 G
b100 4
b10 D
b1000 R
b1 C
b0 B
b11 3
b0 5
b1000 U
b111 0
1,
#170000
0,
#175000
1-
1,
#180000
0,
#185000
1!
b11 "
b11 I
0-
1,
#190000
0,
#195000
b10 "
b10 I
0!
0H
b1000 R
b1 D
b0 C
b0 4
b1 3
b1000 U
b1001 0
1,
#200000
0,
#205000
1-
1,
#210000
0,
#215000
b11 "
b11 I
0-
1,
#220000
0,
#225000
b10 "
b10 I
1H
b1 E
b1000 R
b0 D
b0 3
b1000 2
b1000 U
b1011 0
1,
#230000
0,
#235000
1-
1,
#240000
0,
#245000
1!
b11 "
b11 I
0-
1,
#250000
0,
#255000
b10 "
b10 I
0!
b11 C
b11 G
0H
b111 4
b1000 R
b0 E
b0 2
b1000 U
b1100 0
1,
#260000
0,
#265000
1-
1,
#270000
0,
#275000
b11 "
b11 I
0-
1,
#280000
0,
#285000
b10 "
b10 I
b1 G
b101 F
b1000 R
b0 C
b0 4
b11111 1
b1000 U
b1110 0
1,
#290000
0,
#295000
1-
1,
#300000
0,
#305000
b1 "
b1 I
0-
1,
#310000
0,
#315000
b10 "
b10 I
b1 C
b1000 R
b10 F
b100 4
b11 1
b1000 U
b10000 0
1,
#320000
0,
#325000
1-
1,
#330000
0,
#335000
b1 "
b1 I
0-
1,
#340000
0,
#345000
b10 "
b10 I
b10 G
b1000 R
b10 F
b10 C
b101 4
b1010 1
b1000 U
b10001 0
1,
#350000
0,
#355000
1-
1,
#360000
0,
#365000
0-
1,
#370000
0,
#375000
b1000 R
b0 F
b0 C
b0 1
b0 4
b1000 U
b10010 0
1,
#380000
0,
#385000
1-
1,
#390000
0,
#395000
0-
1,
#400000
0,
#405000
b11 G
1H
b10 C
b110 4
b1 B
b1000 R
b1 5
b1000 U
b10100 0
1,
#410000
0,
#415000
1-
1,
#420000
0,
#425000
1!
b11 "
b11 I
0-
1,
#430000
0,
#435000
b10 "
b10 I
0!
1,
#440000
0,
#445000
1H
b0 4
b1 E
b1000 R
b0 C
b0 B
b10000000 2
b0 5
b1000 U
b10101 0
1,
#450000
0,
#455000
1-
1,
#460000
0,
#465000
1!
b11 "
b11 I
0-
1,
#470000
0,
#475000
b10 "
b10 I
0!
b10110 0
1,
